pwgen_secure/__init__.py
pwgen_secure/fileRandomizer.py
pwgen_secure/rpg.py
pwgen_secure/search_space_calculator.py
pwgen_secure-0.9.0.dist-info/LICENSE
pwgen_secure-0.9.0.dist-info/METADATA
pwgen_secure-0.9.0.dist-info/WHEEL
pwgen_secure-0.9.0.dist-info/top_level.txt
pwgen_secure-0.9.0.dist-info/RECORD
