Metadata-Version: 2.1
Name: pwgen-secure
Version: 0.9.0
Summary: Generate cryptographically secure random passwords with specified character sets, patterns, or lengths.
Home-page: https://github.com/mjmunger/pwgen_secure
Author: Michael Munger
Author-email: mj@hph.io
License: UNKNOWN
Platform: UNKNOWN
Classifier: Topic :: Security
Classifier: Topic :: Security :: Cryptography
Classifier: Development Status :: 5 - Production/Stable
Classifier: Programming Language :: Python :: 3.6
Classifier: License :: OSI Approved :: MIT License
Classifier: Operating System :: OS Independent
